.gitignore
LICENSE
README.md
pyproject.toml
setup.py
ruffsack/__init__.py
ruffsack.egg-info/PKG-INFO
ruffsack.egg-info/SOURCES.txt
ruffsack.egg-info/dependency_links.txt
ruffsack.egg-info/requires.txt
ruffsack.egg-info/top_level.txt