Metadata-Version: 2.1
Name: ruffsack
Version: 0.0.0
Summary: Ruffsack: A rugged multisig wallet for everyday adventures
Author: ApeWorX LTD
Requires-Python: >=3.10
License-File: LICENSE
